{"grades": [
  {
    "grado": "1",
    "score": 2,
    "total": 5,
    "numero": 1,
    "workshopTitle": "Operaciones Básicas con Fracciones",
    "answers": [
      0,
      0,
      0,
      0,
      0
    ],
    "nombre": "james",
    "timestamp": 1780886467937
  },
  {
    "grado": "1",
    "score": 1,
    "total": 5,
    "numero": 1,
    "workshopTitle": "Operaciones Básicas con Fracciones",
    "answers": [
      2,
      0,
      0,
      0,
      0
    ],
    "nombre": "1",
    "timestamp": 1780887850654
  }
]}